zapier/__init__.py
zapier/admin.py
zapier/apps.py
zapier/auth.py
zapier/decorators.py
zapier/exceptions.py
zapier/migrations/0001_initial.py
zapier/migrations/__init__.py
zapier/models.py
zapier/settings.py
zapier/types.py
zapier/urls.py
zapier/views.py
django_zapier_triggers-0.2.3.dist-info/LICENSE
django_zapier_triggers-0.2.3.dist-info/WHEEL
django_zapier_triggers-0.2.3.dist-info/METADATA
django_zapier_triggers-0.2.3.dist-info/RECORD
