Metadata-Version: 2.1
Name: django-zapier-triggers
Version: 0.2.3
Summary: Simple Django app for managing Zapier triggers.
Home-page: https://github.com/yunojuno/django-zapier-trigger
License: MIT
Author: YunoJuno
Author-email: code@yunojuno.com
Maintainer: YunoJuno
Maintainer-email: code@yunojuno.com
Requires-Python: >=3.8,<4.0
Classifier: Development Status :: 4 - Beta
Classifier: Environment :: Web Environment
Classifier: Framework :: Django
Classifier: Framework :: Django :: 3.2
Classifier: Framework :: Django :: 4.0
Classifier: License :: OSI Approved :: MIT License
Classifier: Operating System :: OS Independent
Classifier: Programming Language :: Python :: 3
Classifier: Programming Language :: Python :: 3 :: Only
Classifier: Programming Language :: Python :: 3.10
Classifier: Programming Language :: Python :: 3.8
Classifier: Programming Language :: Python :: 3.9
Requires-Dist: django (>=3.2,<5.0)
Requires-Dist: python-dateutil
Project-URL: Documentation, https://github.com/yunojuno/pdjango-zapier-trigger
Project-URL: Repository, https://github.com/yunojuno/django-zapier-trigger
